{
  "subtitles_with_timestamps": [
    {
      "start": 480.062,
      "end": 482.189,
      "text": "...can also be used as a phone."
    },
    {
      "start": 484.275,
      "end": 485.734,
      "text": "[PHONE RINGS]"
    },
    {
      "start": 486.235,
      "end": 487.569,
      "text": "Yes, it's working."
    },
    {
      "start": 489.906,
      "end": 491.281,
      "text": "Why isn't she calling me back?"
    },
    {
      "start": 491.866,
      "end": 493.366,
      "text": "Maybe she never got your message."
    },
    {
      "start": 493.534,
      "end": 496.995,
      "text": "You know, you could call her machine, and if she has a lot of beeps..."
    },
    {
      "start": 497.163,
      "end": 499.998,
      "text": "...that means she probably didn't get her messages yet."
    },
    {
      "start": 500.166,
      "end": 503.96,
      "text": "- You don't think that makes me seem...? - Desperate? Needy? Pathetic?"
    },
    {
      "start": 504.921,
      "end": 507.422,
      "text": "Ah, you obviously saw my personal ad."
    },
    {
      "start": 510.593,
      "end": 513.011,
      "text": "- How many beeps? - She answered."
    },
    {
      "start": 514.889,
      "end": 518.183,
      "text": "You see, this is where you'd use that \"hello\" word we talked about."
    },
    {
      "start": 519.06,
      "end": 521.186,
      "text": "I'm not going to. She obviously got my message..."
    },
    {
      "start": 521.354,
      "end": 525.232,
      "text": "...and is choosing not to call me. Now I'm needy and snubbed."
    },
    {
      "start": 526.692,
      "end": 528.985,
      "text": "God, I miss just being needy."
    },
    {
      "start": 530.279,
      "end": 531.404,
      "text": "GROUP: Hey."
    },
    {
      "start": 531.572,
      "end": 533.198,
      "text": "So how'd he take it?"
    },
    {
      "start": 533.366,
      "end": 535.784,
      "text": "Pretty well, actually."
    },
    {
      "start": 537.2860000000001,
      "end": 541.831,
      "text": "Uh, Rach. How come you have dental floss in your hair?"
    }
  ],
  "subtitles_without_timestamps": [
    "...can also be used as a phone.",
    "[PHONE RINGS]",
    "Yes, it's working.",
    "Why isn't she calling me back?",
    "Maybe she never got your message.",
    "You know, you could call her machine, and if she has a lot of beeps...",
    "...that means she probably didn't get her messages yet.",
    "- You don't think that makes me seem...? - Desperate? Needy? Pathetic?",
    "Ah, you obviously saw my personal ad.",
    "- How many beeps? - She answered.",
    "You see, this is where you'd use that \"hello\" word we talked about.",
    "I'm not going to. She obviously got my message...",
    "...and is choosing not to call me. Now I'm needy and snubbed.",
    "God, I miss just being needy.",
    "GROUP: Hey.",
    "So how'd he take it?",
    "Pretty well, actually.",
    "Uh, Rach. How come you have dental floss in your hair?"
  ]
}