{
  "subtitles_with_timestamps": [
    {
      "start": 719.009,
      "end": 722.303,
      "text": "This is so typical. I'm always the last to know everything."
    },
    {
      "start": 722.555,
      "end": 725.223,
      "text": "- You are not. We tell you stuff. - Uh-huh."
    },
    {
      "start": 725.391,
      "end": 730.019,
      "text": "I was the last one to know when Chandler got bit by the peacock at the zoo."
    },
    {
      "start": 730.771,
      "end": 733.815,
      "text": "I was the last to know you had a crush on Joey when he was moving in."
    },
    {
      "start": 733.983,
      "end": 735.525,
      "text": "What?"
    },
    {
      "start": 736.068,
      "end": 738.82,
      "text": "Oh. Looks like I was second to last."
    },
    {
      "start": 744.452,
      "end": 746.244,
      "text": "It's so nice."
    },
    {
      "start": 750.875,
      "end": 752.7090000000001,
      "text": "Hey, I have a question."
    },
    {
      "start": 754.378,
      "end": 756.921,
      "text": "Uh, actually, it's not so much a question..."
    },
    {
      "start": 757.173,
      "end": 759.799,
      "text": "...it's more of a general wondering..."
    },
    {
      "start": 760.801,
      "end": 762.093,
      "text": "...ment."
    },
    {
      "start": 762.928,
      "end": 764.721,
      "text": "- Okay. - Okay."
    },
    {
      "start": 765.306,
      "end": 766.89,
      "text": "Here goes."
    },
    {
      "start": 768.893,
      "end": 773.354,
      "text": "Um, well, for a while now, I've been wanting to, um..."
    },
    {
      "start": 773.731,
      "end": 776.191,
      "text": "- Oh. - Yes, that's right."
    },
    {
      "start": 776.4,
      "end": 778.735,
      "text": "Look at that little kitty."
    },
    {
      "start": 778.986,
      "end": 780.028,
      "text": "What?"
    }
  ],
  "subtitles_without_timestamps": [
    "This is so typical. I'm always the last to know everything.",
    "- You are not. We tell you stuff. - Uh-huh.",
    "I was the last one to know when Chandler got bit by the peacock at the zoo.",
    "I was the last to know you had a crush on Joey when he was moving in.",
    "What?",
    "Oh. Looks like I was second to last.",
    "It's so nice.",
    "Hey, I have a question.",
    "Uh, actually, it's not so much a question...",
    "...it's more of a general wondering...",
    "...ment.",
    "- Okay. - Okay.",
    "Here goes.",
    "Um, well, for a while now, I've been wanting to, um...",
    "- Oh. - Yes, that's right.",
    "Look at that little kitty.",
    "What?"
  ]
}