{
  "subtitles_with_timestamps": [
    {
      "start": 658.366,
      "end": 661.368,
      "text": "It's really pretty. Unfortunately, I don't see suds!"
    },
    {
      "start": 663.913,
      "end": 664.954,
      "text": "What?"
    },
    {
      "start": 666.123,
      "end": 669.292,
      "text": "No suds, no save, okay?"
    },
    {
      "start": 672.171,
      "end": 673.63,
      "text": "- What's going on? - Hi."
    },
    {
      "start": 673.839,
      "end": 677.592,
      "text": "Nothing. This horrible woman just took my machine."
    },
    {
      "start": 677.885,
      "end": 679.344,
      "text": "Was your basket on top?"
    },
    {
      "start": 679.595,
      "end": 681.805,
      "text": "- Yeah, but there were no suds. - So?"
    },
    {
      "start": 682.056,
      "end": 683.556,
      "text": "You know, no suds, no save."
    },
    {
      "start": 683.808,
      "end": 685.767,
      "text": "No suds, no... Excuse me."
    },
    {
      "start": 686.018,
      "end": 687.602,
      "text": "Hold on a second!"
    },
    {
      "start": 687.812,
      "end": 689.979,
      "text": "This is my friend's machine."
    },
    {
      "start": 690.231,
      "end": 692.399,
      "text": "Hey, hey, hey! Her stuff wasn't in it!"
    },
    {
      "start": 692.65,
      "end": 696.653,
      "text": "Hey, hey, hey! That's not the rule, and you know it!"
    },
    {
      "start": 707.164,
      "end": 708.707,
      "text": "All right. Show's over."
    },
    {
      "start": 711.669,
      "end": 713.878,
      "text": "Nothing to see here."
    },
    {
      "start": 716.298,
      "end": 718.466,
      "text": "Okay. Let's do laundry."
    },
    {
      "start": 718.676,
      "end": 722.47,
      "text": "That was amazing! I can't even send back soup."
    }
  ],
  "subtitles_without_timestamps": [
    "It's really pretty. Unfortunately, I don't see suds!",
    "What?",
    "No suds, no save, okay?",
    "- What's going on? - Hi.",
    "Nothing. This horrible woman just took my machine.",
    "Was your basket on top?",
    "- Yeah, but there were no suds. - So?",
    "You know, no suds, no save.",
    "No suds, no... Excuse me.",
    "Hold on a second!",
    "This is my friend's machine.",
    "Hey, hey, hey! Her stuff wasn't in it!",
    "Hey, hey, hey! That's not the rule, and you know it!",
    "All right. Show's over.",
    "Nothing to see here.",
    "Okay. Let's do laundry.",
    "That was amazing! I can't even send back soup."
  ]
}