{
  "subtitles_with_timestamps": [
    {
      "start": 779.779,
      "end": 783.364,
      "text": "Congratulations. I think you found the world's thinnest argument."
    },
    {
      "start": 784.033,
      "end": 785.992,
      "text": "I'm just trying to find the right moment."
    },
    {
      "start": 786.243,
      "end": 789.287,
      "text": "Oh, well, that shouldn't be so hard, now that you're dating."
    },
    {
      "start": 790.706,
      "end": 795.043,
      "text": "\"Sweetheart, you're fired. But how about a quickie before I go to work?\""
    },
    {
      "start": 798.672,
      "end": 799.798,
      "text": "- Hey. - Hey."
    },
    {
      "start": 800.299,
      "end": 801.674,
      "text": "[KNOCK ON DOOR]"
    },
    {
      "start": 802.718,
      "end": 805.97,
      "text": "Once you're inside, you don't have to knock anymore."
    },
    {
      "start": 807.264,
      "end": 808.681,
      "text": "I'll get it."
    },
    {
      "start": 812.061,
      "end": 813.895,
      "text": "Oh. Hi, Mr. Heckles."
    },
    {
      "start": 814.48,
      "end": 815.522,
      "text": "You're doing it again."
    },
    {
      "start": 815.731,
      "end": 817.232,
      "text": "We're not doing anything."
    },
    {
      "start": 817.441,
      "end": 820.568,
      "text": "We're just sitting around talking quietly."
    },
    {
      "start": 820.861,
      "end": 822.862,
      "text": "I can hear you through the ceiling."
    },
    {
      "start": 824.782,
      "end": 826.825,
      "text": "My cats can't sleep."
    },
    {
      "start": 828.5360000000001,
      "end": 830.245,
      "text": "You don't even have cats."
    },
    {
      "start": 830.454,
      "end": 832.372,
      "text": "I could have cats."
    },
    {
      "start": 833.9159999999999,
      "end": 835.124,
      "text": "Goodbye, Mr. Heckles."
    },
    {
      "start": 835.3340000000001,
      "end": 837.877,
      "text": "We'll try to keep it down."
    }
  ],
  "subtitles_without_timestamps": [
    "Congratulations. I think you found the world's thinnest argument.",
    "I'm just trying to find the right moment.",
    "Oh, well, that shouldn't be so hard, now that you're dating.",
    "\"Sweetheart, you're fired. But how about a quickie before I go to work?\"",
    "- Hey. - Hey.",
    "[KNOCK ON DOOR]",
    "Once you're inside, you don't have to knock anymore.",
    "I'll get it.",
    "Oh. Hi, Mr. Heckles.",
    "You're doing it again.",
    "We're not doing anything.",
    "We're just sitting around talking quietly.",
    "I can hear you through the ceiling.",
    "My cats can't sleep.",
    "You don't even have cats.",
    "I could have cats.",
    "Goodbye, Mr. Heckles.",
    "We'll try to keep it down."
  ]
}