{
  "subtitles_with_timestamps": [
    {
      "start": 600.266,
      "end": 601.975,
      "text": "Can you believe this happened?"
    },
    {
      "start": 602.226,
      "end": 603.685,
      "text": "No, no."
    },
    {
      "start": 605.062,
      "end": 606.605,
      "text": "And yet it did."
    },
    {
      "start": 607.523,
      "end": 609.774,
      "text": "- Goodbye, Janice. - Kiss me."
    },
    {
      "start": 612.653,
      "end": 617.532,
      "text": "Oh, Chandler. Sorry."
    },
    {
      "start": 619.66,
      "end": 621.87,
      "text": "- Hey, Janice. - Hi, Monica."
    },
    {
      "start": 622.079,
      "end": 624.998,
      "text": "Okay. Well, this was very special."
    },
    {
      "start": 626.208,
      "end": 629.127,
      "text": "Rach, come see who's out here."
    },
    {
      "start": 629.629,
      "end": 632.505,
      "text": "What's going on...? Oh, my God."
    },
    {
      "start": 632.715,
      "end": 634.883,
      "text": "Janice. Hi."
    },
    {
      "start": 635.384,
      "end": 638.053,
      "text": "Janice is gonna go away now."
    },
    {
      "start": 639.972,
      "end": 641.056,
      "text": "I'll be right back."
    },
    {
      "start": 641.474,
      "end": 645.268,
      "text": "Oh. Joey. Look who it is."
    },
    {
      "start": 645.853,
      "end": 647.103,
      "text": "Whoa."
    },
    {
      "start": 649.44,
      "end": 650.982,
      "text": "Oh, good. Joey's home now."
    },
    {
      "start": 651.233,
      "end": 653.568,
      "text": "This is so much fun."
    },
    {
      "start": 653.819,
      "end": 656.154,
      "text": "This is like a reunion in the hall."
    },
    {
      "start": 656.322,
      "end": 658.198,
      "text": "[LAUGHS]"
    },
    {
      "start": 658.949,
      "end": 662.035,
      "text": "Hi, Ross. There's someone I want you to say hi to."
    }
  ],
  "subtitles_without_timestamps": [
    "Can you believe this happened?",
    "No, no.",
    "And yet it did.",
    "- Goodbye, Janice. - Kiss me.",
    "Oh, Chandler. Sorry.",
    "- Hey, Janice. - Hi, Monica.",
    "Okay. Well, this was very special.",
    "Rach, come see who's out here.",
    "What's going on...? Oh, my God.",
    "Janice. Hi.",
    "Janice is gonna go away now.",
    "I'll be right back.",
    "Oh. Joey. Look who it is.",
    "Whoa.",
    "Oh, good. Joey's home now.",
    "This is so much fun.",
    "This is like a reunion in the hall.",
    "[LAUGHS]",
    "Hi, Ross. There's someone I want you to say hi to."
  ]
}