{
  "subtitles_with_timestamps": [
    {
      "start": 361.527,
      "end": 362.694,
      "text": "I don't know."
    },
    {
      "start": 362.862,
      "end": 368.2,
      "text": "Look, he's a great guy, and I love being with him, but, you know..."
    },
    {
      "start": 368.368,
      "end": 369.951,
      "text": "...things happen when they happen."
    },
    {
      "start": 370.119,
      "end": 371.62,
      "text": "You don't plan these things."
    },
    {
      "start": 373.748,
      "end": 376.291,
      "text": "- Oh. So did you shave your legs? - Yeah."
    },
    {
      "start": 376.501,
      "end": 377.709,
      "text": "Uh-huh."
    },
    {
      "start": 380.463,
      "end": 383.507,
      "text": "Would you let it go, Ross? It was just a dream."
    },
    {
      "start": 383.716,
      "end": 384.8,
      "text": "It doesn't mean..."
    },
    {
      "start": 384.967,
      "end": 386.009,
      "text": "[BEEPER BEEPING]"
    },
    {
      "start": 386.177,
      "end": 389.721,
      "text": "Oh, oh, oh. Oh, this is it. Oh, my God. It's baby time. Baby time."
    },
    {
      "start": 389.889,
      "end": 393.266,
      "text": "All right, relax, relax, just relax, just relax. Be cool."
    },
    {
      "start": 394.519,
      "end": 396.812,
      "text": "Yeah, hi, I was just beeped."
    },
    {
      "start": 398.147,
      "end": 402.901,
      "text": "No, Andre is not here. Third time today."
    },
    {
      "start": 403.069,
      "end": 405.153,
      "text": "Yes, I am sure."
    },
    {
      "start": 405.321,
      "end": 409.324,
      "text": "Heh. No, sir, I do not perform those kind of services."
    },
    {
      "start": 409.492,
      "end": 413.078,
      "text": "Services? Oh, services."
    },
    {
      "start": 413.246,
      "end": 416.373,
      "text": "Yeah, you want 55-JUMBO."
    },
    {
      "start": 418.543,
      "end": 420.043,
      "text": "Yeah."
    }
  ],
  "subtitles_without_timestamps": [
    "I don't know.",
    "Look, he's a great guy, and I love being with him, but, you know...",
    "...things happen when they happen.",
    "You don't plan these things.",
    "- Oh. So did you shave your legs? - Yeah.",
    "Uh-huh.",
    "Would you let it go, Ross? It was just a dream.",
    "It doesn't mean...",
    "[BEEPER BEEPING]",
    "Oh, oh, oh. Oh, this is it. Oh, my God. It's baby time. Baby time.",
    "All right, relax, relax, just relax, just relax. Be cool.",
    "Yeah, hi, I was just beeped.",
    "No, Andre is not here. Third time today.",
    "Yes, I am sure.",
    "Heh. No, sir, I do not perform those kind of services.",
    "Services? Oh, services.",
    "Yeah, you want 55-JUMBO.",
    "Yeah."
  ]
}