{
  "subtitles_with_timestamps": [
    {
      "start": 1021.77,
      "end": 1025.231,
      "text": "Wait! You forgot your legs!"
    },
    {
      "start": 1025.983,
      "end": 1028.026,
      "text": "ALL: Push. Push. - We're here!"
    },
    {
      "start": 1028.193,
      "end": 1029.861,
      "text": "[ALL SHOUTING INDISTINCTLY]"
    },
    {
      "start": 1030.029,
      "end": 1032.822,
      "text": "ROSS: We're here. - Where have you been?!"
    },
    {
      "start": 1032.99,
      "end": 1034.115,
      "text": "Long story, honey."
    },
    {
      "start": 1034.283,
      "end": 1036.451,
      "text": "FRANZBLAU: All right, Carol, I need you to keep pushing."
    },
    {
      "start": 1036.618,
      "end": 1038.411,
      "text": "I need... Excuse me, can I have this?"
    },
    {
      "start": 1038.662,
      "end": 1040.246,
      "text": "Oh, sorry."
    },
    {
      "start": 1040.456,
      "end": 1041.664,
      "text": "All right, all right."
    },
    {
      "start": 1041.832,
      "end": 1044.917,
      "text": "There's too many people in this room. There's about to be one more."
    },
    {
      "start": 1045.085,
      "end": 1049.464,
      "text": "So anybody who's not an ex-husband or a lesbian life partner, out you go."
    },
    {
      "start": 1049.631,
      "end": 1051.34,
      "text": "- Come on, out. RACHEL: Okay, good luck."
    },
    {
      "start": 1051.508,
      "end": 1053.676,
      "text": "- Bye, bye, bye. - Good luck, you guys, good luck."
    },
    {
      "start": 1053.886,
      "end": 1057.805,
      "text": "Let me ask you, do you have to be Carol's lesbian life partner?"
    },
    {
      "start": 1057.973,
      "end": 1059.515,
      "text": "NURSE: Out."
    },
    {
      "start": 1060.809,
      "end": 1063.227,
      "text": "FRANZBLAU: All right. All right, he's crowning. Here he comes."
    },
    {
      "start": 1063.395,
      "end": 1066.23,
      "text": "Let me see. I gotta see, I gotta see."
    },
    {
      "start": 1066.398,
      "end": 1068.066,
      "text": "Oh... Oh."
    },
    {
      "start": 1069.902,
      "end": 1071.319,
      "text": "Oh! A head."
    },
    {
      "start": 1071.487,
      "end": 1074.489,
      "text": "Oh. It's huge. Carol, how are you doing this?"
    },
    {
      "start": 1075.783,
      "end": 1077.825,
      "text": "Not helping."
    },
    {
      "start": 1078.035,
      "end": 1079.952,
      "text": "FRANZBLAU: You're doing great. You're doing fine."
    }
  ],
  "subtitles_without_timestamps": [
    "Wait! You forgot your legs!",
    "ALL: Push. Push. - We're here!",
    "[ALL SHOUTING INDISTINCTLY]",
    "ROSS: We're here. - Where have you been?!",
    "Long story, honey.",
    "FRANZBLAU: All right, Carol, I need you to keep pushing.",
    "I need... Excuse me, can I have this?",
    "Oh, sorry.",
    "All right, all right.",
    "There's too many people in this room. There's about to be one more.",
    "So anybody who's not an ex-husband or a lesbian life partner, out you go.",
    "- Come on, out. RACHEL: Okay, good luck.",
    "- Bye, bye, bye. - Good luck, you guys, good luck.",
    "Let me ask you, do you have to be Carol's lesbian life partner?",
    "NURSE: Out.",
    "FRANZBLAU: All right. All right, he's crowning. Here he comes.",
    "Let me see. I gotta see, I gotta see.",
    "Oh... Oh.",
    "Oh! A head.",
    "Oh. It's huge. Carol, how are you doing this?",
    "Not helping.",
    "FRANZBLAU: You're doing great. You're doing fine."
  ]
}